FuyaoCountdown/__init__.py
FuyaoCountdown/countdown.py
FuyaoCountdown/utils/__init__.py
fuyaocountdown-0.0.2.dist-info/licenses/LICENSE
fuyaocountdown-0.0.2.dist-info/METADATA
fuyaocountdown-0.0.2.dist-info/WHEEL
fuyaocountdown-0.0.2.dist-info/top_level.txt
fuyaocountdown-0.0.2.dist-info/RECORD
