Metadata-Version: 2.4
Name: FuyaoCountdown
Version: 0.0.2
Summary: 一个可以在到达目标时间时执行任务的第三方库
Author-email: fuyao-norway <1959415641@qq.com>, fuyao-ziqiu <1987239025@qq.com>, fuyaoteam <fuyaoteam@gmail.com>
License: MIT License
Project-URL: Repository, https://github.com/fuyao-lhw/FuyaoCountdown
Classifier: Programming Language :: Python :: 3
Classifier: License :: OSI Approved :: MIT License
Requires-Python: >=3.10.7
License-File: LICENSE
Requires-Dist: pathlib>=1.0.1
Dynamic: license-file
